setup.cfg
setup.py
weaknet.py
test/test_speed.py
weaknet.egg-info/PKG-INFO
weaknet.egg-info/SOURCES.txt
weaknet.egg-info/dependency_links.txt
weaknet.egg-info/entry_points.txt
weaknet.egg-info/top_level.txt