Metadata-Version: 1.1
Name: weaknet
Version: 1.7.9.1
Summary: Tiny safety network proxy tools
Home-page: https://github.com/vietor/pyweaknet
Author: Vietor Liu
Author-email: vietor.liu@gmail.com
License: MIT
Download-URL: https://github.com/vietor/pyweaknet/tarball/1.7.9.1
Keywords: proxy,weaknet,shadowsocks,ss
Platform: UNKNOWN
Classifier: Programming Language :: Python
Classifier: Programming Language :: Python :: 2
Classifier: Programming Language :: Python :: 3
Classifier: Development Status :: 5 - Production/Stable
Classifier: Natural Language :: English
Classifier: Environment :: Console
Classifier: Intended Audience :: System Administrators
Classifier: License :: OSI Approved :: MIT License
Requires: python (>=2.6.0)
